Debrato_IT_A_62/Debrato_IT_A_62_DISL/Lab_6/Q1/decoder2to4.v
module decoder2to4 (
    input wire en,          
    input wire [1:0] in,    
    output reg [3:0] y    
);

always @(*) begin
    if (en) begin
        if (in == 2'b00)
            y = 4'b0001;
        else if (in == 2'b01)
            y = 4'b0010;
        else if (in == 2'b10)
            y = 4'b0100;
        else
            y = 4'b1000;
    end 
    else begin
        y = 4'b0000; 
    end
end
endmodule

module decoder3to8 (
    input wire en,           
    input wire [2:0] in,     
    output wire [7:0] y      
);

wire [3:0] y_low, y_high; 

decoder2to4 dec_low (
    .en(en & ~in[2]),      
    .in(in[1:0]),
    .y(y_low)
);

 
decoder2to4 dec_high (
    .en(en & in[2]),          
    .in(in[1:0]),
    .y(y_high)
);

assign y = {y_high, y_low};
endmodule

Debrato_IT_A_62/Debrato_IT_A_62_DISL/Lab_6/Q1/decoder_tb.v
`timescale 1ns/1ns
`include "decoder2to4.v"
module decoder_tb;
reg en;
reg [2:0] in;
wire [7:0] y;

decoder3to8 uut (
    .en(en),
    .in(in),
    .y(y)
);

initial begin
    $dumpfile("decoder_tb.vcd");
    $dumpvars(0, decoder_tb);
    $display("Time | en in  | y");
    $display("------------------------");

    en = 0;
    in = 3'b000;
    #5;

    $display("%0t | %b  %b | %b", $time, en, in, y);
    repeat (8) begin
        in = in + 1;
        #5;
        $display("%0t | %b  %b | %b", $time, en, in, y);
    end

    en = 1;
    in = 3'b000;
    #5;

    repeat (8) begin
        $display("%0t | %b  %b | %b", $time, en, in, y);
        in = in + 1;
        #5;
    end

    $finish;
end

endmodule

Debrato_IT_A_62/Debrato_IT_A_62_DISL/Lab_6/Q1/decoder_tb.vcd
$date
	Tue Sep 23 08:40:35 2025
$end
$version
	Icarus Verilog
$end
$timescale
	1ns
$end
$scope module decoder_tb $end
$var wire 8 ! y [7:0] $end
$var reg 1 " en $end
$var reg 3 # in [2:0] $end
$scope module uut $end
$var wire 1 " en $end
$var wire 3 $ in [2:0] $end
$var wire 4 % y_low [3:0] $end
$var wire 4 & y_high [3:0] $end
$var wire 8 ' y [7:0] $end
$scope module dec_high $end
$var wire 1 ( en $end
$var wire 2 ) in [1:0] $end
$var reg 4 * y [3:0] $end
$upscope $end
$scope module dec_low $end
$var wire 1 + en $end
$var wire 2 , in [1:0] $end
$var reg 4 - y [3:0] $end
$upscope $end
$upscope $end
$upscope $end
$enddefinitions $end
$comment Show the parameter values. $end
$dumpall
$end
#0
$dumpvars
b0 -
b0 ,
0+
b0 *
b0 )
0(
b0 '
b0 &
b0 %
b0 $
b0 #
0"
b0 !
$end
#5
b1 ,
b1 )
b1 #
b1 $
#10
b10 ,
b10 )
b10 #
b10 $
#15
b11 ,
b11 )
b11 #
b11 $
#20
b0 ,
b0 )
b100 #
b100 $
#25
b1 ,
b1 )
b101 #
b101 $
#30
b10 ,
b10 )
b110 #
b110 $
#35
b11 ,
b11 )
b111 #
b111 $
#40
b0 ,
b0 )
b0 #
b0 $
#45
b1 !
b1 '
b1 %
b1 -
1+
1"
#50
b10 !
b10 '
b10 %
b10 -
b1 ,
b1 )
b1 #
b1 $
#55
b100 !
b100 '
b100 %
b100 -
b10 ,
b10 )
b10 #
b10 $
#60
b1000 !
b1000 '
b1000 %
b1000 -
b11 ,
b11 )
b11 #
b11 $
#65
0+
b1 &
b1 *
b10000 !
b10000 '
b0 %
b0 -
1(
b0 ,
b0 )
b100 #
b100 $
#70
b100000 !
b100000 '
b10 &
b10 *
b1 ,
b1 )
b101 #
b101 $
#75
b1000000 !
b1000000 '
b100 &
b100 *
b10 ,
b10 )
b110 #
b110 $
#80
b10000000 !
b10000000 '
b1000 &
b1000 *
b11 ,
b11 )
b111 #
b111 $
#85
b1 %
b1 -
1+
0(
b1 !
b1 '
b0 &
b0 *
b0 ,
b0 )
b0 #
b0 $
