Debrato_IT_A_62/Debrato_IT_A_62_DISL/Lab_3/ex1/ex1.v
module ex1(a, b, c, d, f);
input a,b,c,d;
output f;
nand(g,a,a);
nand(h,b,b);
nand(i,c,c);
nand(j,g,i);
nand(k,g,d);
nand(l,b,d);
nand(m,b,i);
nand(f,j,k,l,m);
endmodule

Debrato_IT_A_62_DISL/Lab_3/ex1/ex1_tb.v
`timescale 1ns/1ns
`include "ex1.v"    //Name of the Verilog file

module ex1_tb();
reg a,b,c,d;		//Input
wire f;			//Output
ex1 ex(a, b, c, d, f);	//Instantiation of the module
initial
begin

	$dumpfile("ex1_tb.vcd");
	$dumpvars(0, ex1_tb);
	
	a=1'b0; b=1'b0; c=1'b0;d=1'b0;
	#20;
	a=1'b0; b=1'b0; c=1'b0;d=1'b1;
	#20;
	a=1'b0; b=1'b0; c=1'b1;d=1'b0;
	#20;
	a=1'b0; b=1'b0; c=1'b1;d=1'b1;
	#20;
	a=1'b0; b=1'b1; c=1'b0;d=1'b0;
	#20;
	a=1'b0; b=1'b1; c=1'b0;d=1'b1;
	#20;
	a=1'b0; b=1'b1; c=1'b1;d=1'b0;
	#20;
	a=1'b0; b=1'b1; c=1'b1;d=1'b1;
	#20;
	a=1'b1; b=1'b0; c=1'b0;d=1'b0;
	#20;
	a=1'b1; b=1'b0; c=1'b0;d=1'b1;
	#20;
	a=1'b1; b=1'b0; c=1'b1;d=1'b0;
	#20;
	a=1'b1; b=1'b0; c=1'b1;d=1'b1;
	#20;
	a=1'b1; b=1'b1; c=1'b0;d=1'b0;
	#20;
	a=1'b1; b=1'b1; c=1'b0;d=1'b1;
	#20;
	a=1'b1; b=1'b1; c=1'b1;d=1'b0;
	#20;
	a=1'b1; b=1'b1; c=1'b1;d=1'b1;
	#20;
	

	
	$display("Test complete");
end

endmodule

Debrato_IT_A_62/Debrato_IT_A_62_DISL/Lab_3/ex1/ex1_tb.vcd
$date
	Tue Aug 12 08:33:37 2025
$end
$version
	Icarus Verilog
$end
$timescale
	1ns
$end
$scope module ex1_tb $end
$var wire 1 ! f $end
$var reg 1 " a $end
$var reg 1 # b $end
$var reg 1 $ c $end
$var reg 1 % d $end
$scope module ex $end
$var wire 1 " a $end
$var wire 1 # b $end
$var wire 1 $ c $end
$var wire 1 % d $end
$var wire 1 ! f $end
$upscope $end
$upscope $end
$enddefinitions $end
#0
$dumpvars
0%
0$
0#
0"
1!
$end
#20
1%
#40
0!
0%
1$
#60
1!
1%
#80
0%
0$
1#
#100
1%
#120
0!
0%
1$
#140
1!
1%
#160
0!
0%
0$
0#
1"
#180
1%
#200
0%
1$
#220
1%
#240
1!
0%
0$
1#
#260
1%
#280
0!
0%
1$
#300
1!
1%
