Debrato_IT_A_62/Debrato_IT_A_62_DISL/Lab_5/Q3/Q3.v
`timescale 1ns / 1ns

// 4-to-1 multiplexer using conditional operator
module mux4to1_cond (
    input wire [3:0] w,   // 4 inputs: w[0], w[1], w[2], w[3]
    input wire [1:0] s,   // 2-bit select
    output wire f
);
    assign f = (s == 2'b00) ? w[0] :
               (s == 2'b01) ? w[1] :
               (s == 2'b10) ? w[2] :
                              w[3];
endmodule


// 16-to-1 multiplexer using hierarchical 4-to-1 mux modules
module mux16to1 (
    input wire [15:0] w,    // 16 inputs: w[0] to w[15]
    input wire [3:0] s,     // 4-bit select
    output wire f
);

    wire [3:0] mux_out;

    // Four 4-to-1 muxes select within groups of 4 inputs using s[1:0]
    mux4to1_cond mux0 (.w(w[3:0]),   .s(s[1:0]), .f(mux_out[0]));
    mux4to1_cond mux1 (.w(w[7:4]),   .s(s[1:0]), .f(mux_out[1]));
    mux4to1_cond mux2 (.w(w[11:8]),  .s(s[1:0]), .f(mux_out[2]));
    mux4to1_cond mux3 (.w(w[15:12]), .s(s[1:0]), .f(mux_out[3]));

    // Final 4-to-1 mux selects among the intermediate outputs using s[3:2]
    mux4to1_cond mux_final (.w(mux_out), .s(s[3:2]), .f(f));

endmodule

Debrato_IT_A_62/Debrato_IT_A_62_DISL/Lab_5/Q3/Q3_tb.v
`timescale 1ns / 1ns
`include "Q3.v"
module Q3_tb;

  reg [15:0] w;
  reg [3:0] s;
  wire f;

  // Instantiate the 16-to-1 mux
  mux16to1 uut (
    .w(w),
    .s(s),
    .f(f)
  );

  integer i;

  initial begin
    $dumpfile("Q3_tb.vcd");
    $dumpvars(0, Q3_tb);

    // Initialize inputs
    w = 16'b0;
    s = 4'b0;
    #10;

    // Test all select lines, setting only one input high at a time to check output
    for (i = 0; i < 16; i = i + 1) begin
      w = 16'b0;
      w[i] = 1'b1;   // Only one input active at a time
      s = i[3:0];    // Select the input
      #20;
      $display("Select = %b, Inputs = %b, Output = %b", s, w, f);
      if (f !== 1'b1) begin
        $display("ERROR: Output mismatch for select %b", s);
      end
    end

    $display("Test complete.");
    $finish;
  end

endmodule

Debrato_IT_A_62/Debrato_IT_A_62_DISL/Lab_5/Q3/Q3_tb.vcd
$date
	Tue Sep  2 09:24:23 2025
$end
$version
	Icarus Verilog
$end
$timescale
	1ns
$end
$scope module Q3_tb $end
$var wire 1 ! f $end
$var reg 4 " s [3:0] $end
$var reg 16 # w [15:0] $end
$var integer 32 $ i [31:0] $end
$scope module uut $end
$var wire 4 % s [3:0] $end
$var wire 16 & w [15:0] $end
$var wire 4 ' mux_out [3:0] $end
$var wire 1 ! f $end
$scope module mux0 $end
$var wire 2 ( s [1:0] $end
$var wire 4 ) w [3:0] $end
$var wire 1 * f $end
$upscope $end
$scope module mux1 $end
$var wire 2 + s [1:0] $end
$var wire 4 , w [3:0] $end
$var wire 1 - f $end
$upscope $end
$scope module mux2 $end
$var wire 2 . s [1:0] $end
$var wire 4 / w [3:0] $end
$var wire 1 0 f $end
$upscope $end
$scope module mux3 $end
$var wire 2 1 s [1:0] $end
$var wire 4 2 w [3:0] $end
$var wire 1 3 f $end
$upscope $end
$scope module mux_final $end
$var wire 2 4 s [1:0] $end
$var wire 4 5 w [3:0] $end
$var wire 1 ! f $end
$upscope $end
$upscope $end
$upscope $end
$enddefinitions $end
#0
$dumpvars
b0 5
b0 4
03
b0 2
b0 1
00
b0 /
b0 .
0-
b0 ,
b0 +
0*
b0 )
b0 (
b0 '
b0 &
b0 %
bx $
b0 #
b0 "
0!
$end
#10
1!
b1 '
b1 5
1*
b1 )
b1 #
b1 &
b0 $
#30
b1 (
b1 +
b1 .
b1 1
b10 )
b1 "
b1 %
b10 #
b10 &
b1 $
#50
b10 (
b10 +
b10 .
b10 1
b100 )
b10 "
b10 %
b100 #
b100 &
b10 $
#70
b11 (
b11 +
b11 .
b11 1
b1000 )
b11 "
b11 %
b1000 #
b1000 &
b11 $
#90
0*
b10 '
b10 5
1-
1!
b0 (
b0 +
b0 .
b0 1
b1 4
b1 ,
b0 )
b100 "
b100 %
b10000 #
b10000 &
b100 $
#110
b1 (
b1 +
b1 .
b1 1
b10 ,
b101 "
b101 %
b100000 #
b100000 &
b101 $
#130
b10 (
b10 +
b10 .
b10 1
b100 ,
b110 "
b110 %
b1000000 #
b1000000 &
b110 $
#150
b11 (
b11 +
b11 .
b11 1
b1000 ,
b111 "
b111 %
b10000000 #
b10000000 &
b111 $
#170
1!
0-
b100 '
b100 5
10
b0 (
b0 +
b0 .
b0 1
b10 4
b1 /
b0 ,
b1000 "
b1000 %
b100000000 #
b100000000 &
b1000 $
#190
b1 (
b1 +
b1 .
b1 1
b10 /
b1001 "
b1001 %
b1000000000 #
b1000000000 &
b1001 $
#210
b10 (
b10 +
b10 .
b10 1
b100 /
b1010 "
b1010 %
b10000000000 #
b10000000000 &
b1010 $
#230
b11 (
b11 +
b11 .
b11 1
b1000 /
b1011 "
b1011 %
b100000000000 #
b100000000000 &
b1011 $
#250
1!
00
b1000 '
b1000 5
13
b0 (
b0 +
b0 .
b0 1
b11 4
b1 2
b0 /
b1100 "
b1100 %
b1000000000000 #
b1000000000000 &
b1100 $
#270
b1 (
b1 +
b1 .
b1 1
b10 2
b1101 "
b1101 %
b10000000000000 #
b10000000000000 &
b1101 $
#290
b10 (
b10 +
b10 .
b10 1
b100 2
b1110 "
b1110 %
b100000000000000 #
b100000000000000 &
b1110 $
#310
b11 (
b11 +
b11 .
b11 1
b1000 2
b1111 "
b1111 %
b1000000000000000 #
b1000000000000000 &
b1111 $
#330
b10000 $
