Debrato_IT_A_62/Debrato_IT_A_62_DISL/Lab_7/Q1/d_ff.v
module d_ff (
  input  wire d,
  input  wire clk,
  input  wire rst,
  output reg  q
);

  always @(posedge clk or posedge rst) begin
    if (rst) begin
      q <= 1'b0;
    end else begin
      q <= d;
    end
  end

endmodule

Debrato_IT_A_62/Debrato_IT_A_62_DISL/Lab_7/Q1/d_ff_tb.v
`timescale 1ns / 1ns
`include "d_ff.v"
module d_ff_tb;

  reg d;
  reg clk;
  reg rst;
  wire q;

  d_ff DUT (
    .d   (d),
    .clk (clk),
    .rst (rst),
    .q   (q)
  );

  localparam PERIOD = 20;

  initial begin
    clk = 1'b0;
    forever #(PERIOD/2) clk = ~clk;
  end

  initial $monitor("MONITOR: %4t | clk=%b | rst=%b | d=%b | q=%b", $time, clk, rst, d, q);

  initial begin
  $dumpfile("d_ff_tb.vcd");
    $dumpvars(0, d_ff_tb);
    d = 1'b0;
    rst = 1'b1;
    $display("Time | clk | rst | d | q");
    $display("--------------------------");

    // 1. Initial reset
    @(posedge clk);
    $display("%4t | %3b | %3b | %1b | %1b", $time, clk, rst, d, q);

    // 2. Deassert reset, set D=1
    #5;
    rst = 1'b0;
    d = 1'b1;
    @(posedge clk);
    $display("%4t | %3b | %3b | %1b | %1b", $time, clk, rst, d, q);

    // 3. Store '1', set D=0 for next cycle
    #5;
    d = 1'b0;
    @(posedge clk);
    $display("%4t | %3b | %3b | %1b | %1b", $time, clk, rst, d, q);

    // 4. Store '0', set D=1 for next cycle
    #5;
    d = 1'b1;
    @(posedge clk);
    $display("%4t | %3b | %3b | %1b | %1b", $time, clk, rst, d, q);

    // 5. Asynchronous reset
    #5;
    d = 1'b0;
    rst = 1'b1;
    #1;
    $display("%4t | %3b | %3b | %1b | %1b (Asyn. Reset)", $time, clk, rst, d, q);

    // 6. Finish simulation
    # (PERIOD * 2);
    $finish;
  end

endmodule

Debrato_IT_A_62/Debrato_IT_A_62_DISL/Lab_7/Q1/d_ff_tb.vcd
$date
	Tue Sep 30 09:02:35 2025
$end
$version
	Icarus Verilog
$end
$timescale
	1ns
$end
$scope module d_ff_tb $end
$var wire 1 ! q $end
$var parameter 32 " PERIOD $end
$var reg 1 # clk $end
$var reg 1 $ d $end
$var reg 1 % rst $end
$scope module DUT $end
$var wire 1 # clk $end
$var wire 1 $ d $end
$var wire 1 % rst $end
$var reg 1 ! q $end
$upscope $end
$upscope $end
$enddefinitions $end
$comment Show the parameter values. $end
$dumpall
b10100 "
$end
#0
$dumpvars
1%
0$
0#
0!
$end
#10
1#
#15
1$
0%
#20
0#
#30
1!
1#
#35
0$
#40
0#
#50
0!
1#
#55
1$
#60
0#
#70
1!
1#
#75
0!
1%
0$
