Debrato_IT_A_62_DISL/Lab_2/ex1/ex1b.v
module ex1b(a, b, c, d, f);
input a,b,c,d;
output f;
assign f=(b&~c&~d)|(~b&d)|(c&~b);
endmodule

Debrato_IT_A_62_DISL/Lab_1/ex1/ex1b_tb.v
`timescale 1ns/1ns
`include "ex1b.v"    //Name of the Verilog file

module ex1b_tb();
reg a,b,c,d;		//Input
wire f;			//Output
ex1b ex(a, b, c, d, f);	//Instantiation of the module
initial
begin

	$dumpfile("ex1b_tb.vcd");
	$dumpvars(0, ex1b_tb);
	
	a=1'b0; b=1'b0; c=1'b0;d=1'b0;
	#20;
	a=1'b0; b=1'b0; c=1'b0;d=1'b1;
	#20;
	a=1'b0; b=1'b0; c=1'b1;d=1'b0;
	#20;
	a=1'b0; b=1'b0; c=1'b1;d=1'b1;
	#20;
	a=1'b0; b=1'b1; c=1'b0;d=1'b0;
	#20;
	a=1'b0; b=1'b1; c=1'b0;d=1'b1;
	#20;
	a=1'b0; b=1'b1; c=1'b1;d=1'b0;
	#20;
	a=1'b0; b=1'b1; c=1'b1;d=1'b1;
	#20;
	a=1'b1; b=1'b0; c=1'b0;d=1'b0;
	#20;
	a=1'b1; b=1'b0; c=1'b0;d=1'b1;
	#20;
	a=1'b1; b=1'b0; c=1'b1;d=1'b0;
	#20;
	a=1'b1; b=1'b0; c=1'b1;d=1'b1;
	#20;
	a=1'b1; b=1'b1; c=1'b0;d=1'b0;
	#20;
	a=1'b1; b=1'b1; c=1'b0;d=1'b1;
	#20;
	a=1'b1; b=1'b1; c=1'b1;d=1'b0;
	#20;
	a=1'b1; b=1'b1; c=1'b1;d=1'b1;
	#20;
	

	
	$display("Test complete");
end

endmodule

Debrato_IT_A_62_DISL/Lab_2/ex1/ex1b_tb.vcd
$date
	Tue Aug  5 08:45:14 2025
$end
$version
	Icarus Verilog
$end
$timescale
	1ns
$end
$scope module ex1b_tb $end
$var wire 1 ! f $end
$var reg 1 " a $end
$var reg 1 # b $end
$var reg 1 $ c $end
$var reg 1 % d $end
$scope module ex $end
$var wire 1 " a $end
$var wire 1 # b $end
$var wire 1 $ c $end
$var wire 1 % d $end
$var wire 1 ! f $end
$upscope $end
$upscope $end
$enddefinitions $end
#0
$dumpvars
0%
0$
0#
0"
1!
$end
#20
1%
#40
0%
1$
#60
1%
#80
0%
0$
1#
#100
0!
1%
#120
0%
1$
#140
1%
#160
0%
0$
0#
1"
#180
1!
1%
#200
0%
1$
#220
1%
#240
1!
0%
0$
1#
#260
0!
1%
#280
0%
1$
#300
1%
