Debrato_IT_A_62_DISL/Lab_1/ex1/ex1a.v
module ex1a(a, b, c, d, f);
input a,b,c,d;
output f;
and (v,a,b);
or (w,v,c);
not (x,w);
and(y,x,d);
or (z,w,d);
and (f,y,z);
endmodule

Debrato_IT_A_62/Debrato_IT_A_62_DISL/Lab_2/ex1/ex1a_tb.v
`timescale 1ns/1ns
`include "ex1a.v"    //Name of the Verilog file

module ex1a_tb();
reg a,b,c,d;		//Input
wire f;			//Output
ex1a ex(a, b, c, d, f);	//Instantiation of the module
initial
begin

	$dumpfile("ex1a_tb.vcd");
	$dumpvars(0, ex1a_tb);
	
	a=1'b0; b=1'b0; c=1'b0;d=1'b0;
	#20;
	a=1'b0; b=1'b0; c=1'b0;d=1'b1;
	#20;
	a=1'b0; b=1'b0; c=1'b1;d=1'b0;
	#20;
	a=1'b0; b=1'b0; c=1'b1;d=1'b1;
	#20;
	a=1'b0; b=1'b1; c=1'b0;d=1'b0;
	#20;
	a=1'b0; b=1'b1; c=1'b0;d=1'b1;
	#20;
	a=1'b0; b=1'b1; c=1'b1;d=1'b0;
	#20;
	a=1'b0; b=1'b1; c=1'b1;d=1'b1;
	#20;
	a=1'b1; b=1'b0; c=1'b0;d=1'b0;
	#20;
	a=1'b1; b=1'b0; c=1'b0;d=1'b1;
	#20;
	a=1'b1; b=1'b0; c=1'b1;d=1'b0;
	#20;
	a=1'b1; b=1'b0; c=1'b1;d=1'b1;
	#20;
	a=1'b1; b=1'b1; c=1'b0;d=1'b0;
	#20;
	a=1'b1; b=1'b1; c=1'b0;d=1'b1;
	#20;
	a=1'b1; b=1'b1; c=1'b1;d=1'b0;
	#20;
	a=1'b1; b=1'b1; c=1'b1;d=1'b1;
	#20;
	

	
	$display("Test complete");
end

endmodule

Debrato_IT_A_62/Debrato_IT_A_62_DISL/Lab_1/ex1/ex1a_tb.vcd
$date
	Tue Jul 29 08:58:03 2025
$end
$version
	Icarus Verilog
$end
$timescale
	1ns
$end
$scope module ex1a_tb $end
$var wire 1 ! f $end
$var reg 1 " a $end
$var reg 1 # b $end
$var reg 1 $ c $end
$var reg 1 % d $end
$scope module ex $end
$var wire 1 " a $end
$var wire 1 # b $end
$var wire 1 $ c $end
$var wire 1 % d $end
$var wire 1 ! f $end
$var wire 1 & v $end
$var wire 1 ' w $end
$var wire 1 ( x $end
$var wire 1 ) y $end
$var wire 1 * z $end
$upscope $end
$upscope $end
$enddefinitions $end
#0
$dumpvars
0*
0)
1(
0'
0&
0%
0$
0#
0"
0!
$end
#20
1!
1)
1*
1%
#40
0!
0(
0)
1'
0%
1$
#60
1%
#80
1(
0*
0'
0%
0$
1#
#100
1!
1)
1*
1%
#120
0!
0(
0)
1'
0%
1$
#140
1%
#160
1(
0*
0'
0%
0$
0#
1"
#180
1!
1)
1*
1%
#200
0!
0(
0)
1'
0%
1$
#220
1%
#240
1&
0%
0$
1#
#260
1%
#280
0%
1$
#300
1%
