Debrato_IT_A_62_DISL/Lab_0/ex1b/ex1b.v
module ex1b(x1, x2, x3, f);
input x1, x2, x3;
output f;
assign f = (x1 & x2) | (x2 & x3);
endmodule

Debrato_IT_A_62/Debrato_IT_A_62_DISL/Lab_0/ex1b/ex1b_tb.v
`timescale 1ns/1ns
`include "ex1b.v"    //Name of the Verilog file

module ex1b_tb();
reg x1, x2, x3;		//Input
wire f;			//Output
ex1b ex(x1, x2, x3, f);	//Instantiation of the module
initial
begin

	$dumpfile("ex1b_tb.vcd");
	$dumpvars(0, ex1b_tb);
	
	x1=1'b0; x2=1'b0; x3=1'b0;
	#20;
	
	x1=1'b0; x2=1'b0; x3=1'b1;
	#20;
	
	x1=1'b0; x2=1'b1; x3=1'b0;
	#20;
	
	x1=1'b0; x2=1'b1; x3=1'b1;
	#20;
	
	x1=1'b1; x2=1'b0; x3=1'b0;
	#20;
	
	x1=1'b1; x2=1'b0; x3=1'b1;
	#20;
	
	x1=1'b1; x2=1'b1; x3=1'b0;
	#20;
	
	x1=1'b1; x2=1'b1; x3=1'b1;
	#20;
	
	$display("Test complete");
end

endmodule

Debrato_IT_A_62/Debrato_IT_A_62_DISL/Lab_0/ex1b/ex1b_tb.vcd
$date
	Tue Jul 22 09:50:01 2025
$end
$version
	Icarus Verilog
$end
$timescale
	1ns
$end
$scope module ex1b_tb $end
$var wire 1 ! f $end
$var reg 1 " x1 $end
$var reg 1 # x2 $end
$var reg 1 $ x3 $end
$scope module ex $end
$var wire 1 ! f $end
$var wire 1 " x1 $end
$var wire 1 # x2 $end
$var wire 1 $ x3 $end
$upscope $end
$upscope $end
$enddefinitions $end
#0
$dumpvars
0$
0#
0"
0!
$end
#20
1$
#40
0$
1#
#60
1!
1$
#80
0!
0$
0#
1"
#100
1$
#120
1!
0$
1#
#140
1$
