Debrato_IT_A_62_DISL/Lab_3/ex4/ex4.v
module ex4 (a, b, c, d, f);
input a,b,c,d;
output f;
assign f=(~a&d)|(~b&~d);
endmodule

Debrato_IT_A_62_DISL/Lab_3/ex4/ex4_tb.v
`timescale 1ns/1ns
`include "ex4.v"    //Name of the Verilog file

module ex4_tb();
reg a,b,c,d;		//Input
wire f;			//Output
ex4 ex(a, b, c, d, f);	//Instantiation of the module
initial
begin

	$dumpfile("ex4_tb.vcd");
	$dumpvars(0, ex4_tb);
	
	a=1'b0; b=1'b0; c=1'b0;d=1'b0;
	#20;
	a=1'b0; b=1'b0; c=1'b0;d=1'b1;
	#20;
	a=1'b0; b=1'b0; c=1'b1;d=1'b0;
	#20;
	a=1'b0; b=1'b0; c=1'b1;d=1'b1;
	#20;
	a=1'b0; b=1'b1; c=1'b0;d=1'b0;
	#20;
	a=1'b0; b=1'b1; c=1'b0;d=1'b1;
	#20;
	a=1'b0; b=1'b1; c=1'b1;d=1'b0;
	#20;
	a=1'b0; b=1'b1; c=1'b1;d=1'b1;
	#20;
	a=1'b1; b=1'b0; c=1'b0;d=1'b0;
	#20;
	a=1'b1; b=1'b0; c=1'b0;d=1'b1;
	#20;
	a=1'b1; b=1'b0; c=1'b1;d=1'b0;
	#20;
	a=1'b1; b=1'b0; c=1'b1;d=1'b1;
	#20;
	a=1'b1; b=1'b1; c=1'b0;d=1'b0;
	#20;
	a=1'b1; b=1'b1; c=1'b0;d=1'b1;
	#20;
	a=1'b1; b=1'b1; c=1'b1;d=1'b0;
	#20;
	a=1'b1; b=1'b1; c=1'b1;d=1'b1;
	#20;
	

	
	$display("Test complete");
end

endmodule

Debrato_IT_A_62/Debrato_IT_A_62_DISL/Lab_3/ex4/ex4_tb.vcd
$date
	Tue Aug 12 09:17:47 2025
$end
$version
	Icarus Verilog
$end
$timescale
	1ns
$end
$scope module ex4_tb $end
$var wire 1 ! f $end
$var reg 1 " a $end
$var reg 1 # b $end
$var reg 1 $ c $end
$var reg 1 % d $end
$scope module ex $end
$var wire 1 " a $end
$var wire 1 # b $end
$var wire 1 $ c $end
$var wire 1 % d $end
$var wire 1 ! f $end
$upscope $end
$upscope $end
$enddefinitions $end
#0
$dumpvars
0%
0$
0#
0"
1!
$end
#20
1%
#40
0%
1$
#60
1%
#80
0!
0%
0$
1#
#100
1!
1%
#120
0!
0%
1$
#140
1!
1%
#160
0%
0$
0#
1"
#180
0!
1%
#200
1!
0%
1$
#220
0!
1%
#240
0%
0$
1#
#260
1%
#280
0%
1$
#300
1%
