Debrato_IT_A_62/Debrato_IT_A_62_DISL/Lab_5/Q4/Q4.v
`timescale 1ns / 1ns

// 2-to-1 multiplexer using conditional operator (used for hierarchy)
module mux2to1 (
    input wire w0, w1,
    input wire s,
    output reg f
);
    always @(*) begin
        if (s)
            f = w1;
        else
            f = w0;
    end
endmodule


// 8-to-1 multiplexer using case statement
module mux8to1_case (
    input wire [7:0] w,
    input wire [2:0] s,
    output reg f
);
    always @(*) begin
        case (s)
            3'b000: f = w[0];
            3'b001: f = w[1];
            3'b010: f = w[2];
            3'b011: f = w[3];
            3'b100: f = w[4];
            3'b101: f = w[5];
            3'b110: f = w[6];
            3'b111: f = w[7];
            default: f = 1'b0;
        endcase
    end
endmodule


// 16-to-1 multiplexer using hierarchical mux8to1 and mux2to1
module mux16to1 (
    input wire [15:0] w,
    input wire [3:0] s,
    output wire f
);

    wire f0, f1;

    // Two 8-to-1 muxes for lower-level selection
    mux8to1_case mux_low (.w(w[7:0]),    .s(s[2:0]), .f(f0));
    mux8to1_case mux_high(.w(w[15:8]),   .s(s[2:0]), .f(f1));

    // Final 2-to-1 mux to select between the two outputs using s[3]
    mux2to1 mux_final (.w0(f0), .w1(f1), .s(s[3]), .f(f));

endmodule

Debrato_IT_A_62/Debrato_IT_A_62_DISL/Lab_5/Q4/Q4_tb.v
`timescale 1ns / 1ns

`include "Q4.v"  // Include the mux modules

module Q4_tb;

    reg [15:0] w;
    reg [3:0] s;
    wire f;

    mux16to1 uut (
        .w(w),
        .s(s),
        .f(f)
    );

    integer i;

    initial begin
        $dumpfile("Q4_tb.vcd");
        $dumpvars(0, Q4_tb);

        w = 16'b0;
        s = 4'b0;
        #10;

        for (i = 0; i < 16; i = i + 1) begin
            w = 16'b0;
            w[i] = 1'b1;
            s = i[3:0];
            #20;
            $display("Select = %b, Input = %b, Output = %b", s, w, f);
            if (f !== 1'b1) begin
                $display("ERROR: Output mismatch at select %b", s);
            end
        end

        $display("Test complete.");
        $finish;
    end
endmodule

Debrato_IT_A_62/Debrato_IT_A_62_DISL/Lab_5/Q4/Q4_tb.vcd
$date
	Tue Sep  2 09:30:03 2025
$end
$version
	Icarus Verilog
$end
$timescale
	1ns
$end
$scope module Q4_tb $end
$var wire 1 ! f $end
$var reg 4 " s [3:0] $end
$var reg 16 # w [15:0] $end
$var integer 32 $ i [31:0] $end
$scope module uut $end
$var wire 4 % s [3:0] $end
$var wire 16 & w [15:0] $end
$var wire 1 ' f1 $end
$var wire 1 ( f0 $end
$var wire 1 ! f $end
$scope module mux_final $end
$var wire 1 ) s $end
$var wire 1 ' w1 $end
$var wire 1 ( w0 $end
$var reg 1 ! f $end
$upscope $end
$scope module mux_high $end
$var wire 3 * s [2:0] $end
$var wire 8 + w [7:0] $end
$var reg 1 ' f $end
$upscope $end
$scope module mux_low $end
$var wire 3 , s [2:0] $end
$var wire 8 - w [7:0] $end
$var reg 1 ( f $end
$upscope $end
$upscope $end
$upscope $end
$enddefinitions $end
#0
$dumpvars
b0 -
b0 ,
b0 +
b0 *
0)
0(
0'
b0 &
b0 %
bx $
b0 #
b0 "
0!
$end
#10
1!
1(
b1 -
b1 #
b1 &
b0 $
#30
b1 ,
b1 *
b10 -
b1 "
b1 %
b10 #
b10 &
b1 $
#50
b10 ,
b10 *
b100 -
b10 "
b10 %
b100 #
b100 &
b10 $
#70
b11 ,
b11 *
b1000 -
b11 "
b11 %
b1000 #
b1000 &
b11 $
#90
b100 ,
b100 *
b10000 -
b100 "
b100 %
b10000 #
b10000 &
b100 $
#110
b101 ,
b101 *
b100000 -
b101 "
b101 %
b100000 #
b100000 &
b101 $
#130
b110 ,
b110 *
b1000000 -
b110 "
b110 %
b1000000 #
b1000000 &
b110 $
#150
b111 ,
b111 *
b10000000 -
b111 "
b111 %
b10000000 #
b10000000 &
b111 $
#170
1'
0(
b0 ,
b0 *
1)
b1 +
b0 -
b1000 "
b1000 %
b100000000 #
b100000000 &
b1000 $
#190
b1 ,
b1 *
b10 +
b1001 "
b1001 %
b1000000000 #
b1000000000 &
b1001 $
#210
b10 ,
b10 *
b100 +
b1010 "
b1010 %
b10000000000 #
b10000000000 &
b1010 $
#230
b11 ,
b11 *
b1000 +
b1011 "
b1011 %
b100000000000 #
b100000000000 &
b1011 $
#250
b100 ,
b100 *
b10000 +
b1100 "
b1100 %
b1000000000000 #
b1000000000000 &
b1100 $
#270
b101 ,
b101 *
b100000 +
b1101 "
b1101 %
b10000000000000 #
b10000000000000 &
b1101 $
#290
b110 ,
b110 *
b1000000 +
b1110 "
b1110 %
b100000000000000 #
b100000000000000 &
b1110 $
#310
b111 ,
b111 *
b10000000 +
b1111 "
b1111 %
b1000000000000000 #
b1000000000000000 &
b1111 $
#330
b10000 $
