Debrato_IT_A_62_DISL/Lab_2/ex3/ex3.v
module ex3(x1, x2, x3, x4, f);
input x1, x2, x3, x4;
output f;
assign f=(x1&x2&x4)|(x2&x3&x4)|(x2&x1&x3)|(x1&x3&x4);
endmodule

Debrato_IT_A_62_DISL/Lab_2/ex3/ex3_tb.v
`timescale 1ns/1ns
`include "ex3.v"    //Name of the Verilog file

module ex3_tb();
reg x1, x2, x3, x4;		//Input
wire f;			//Output
ex3 ex(x1, x2, x3, x4, f);	//Instantiation of the module
initial
begin

	$dumpfile("ex3_tb.vcd");
	$dumpvars(0, ex3_tb);
	
	x1=1'b0; x2=1'b0; x3=1'b0;x4=1'b0;
	#20;
	x1=1'b0; x2=1'b0; x3=1'b0;x4=1'b1;
	#20;
	x1=1'b0; x2=1'b0; x3=1'b1;x4=1'b0;
	#20;
	x1=1'b0; x2=1'b0; x3=1'b1;x4=1'b1;
	#20;
	x1=1'b0; x2=1'b1; x3=1'b0;x4=1'b0;
	#20;
	x1=1'b0; x2=1'b1; x3=1'b0;x4=1'b1;
	#20;
	x1=1'b0; x2=1'b1; x3=1'b1;x4=1'b0;
	#20;
	x1=1'b0; x2=1'b1; x3=1'b1;x4=1'b1;
	#20;
	x1=1'b1; x2=1'b0; x3=1'b0;x4=1'b0;
	#20;
	x1=1'b1; x2=1'b0; x3=1'b0;x4=1'b1;
	#20;
	x1=1'b1; x2=1'b0; x3=1'b1;x4=1'b0;
	#20;
	x1=1'b1; x2=1'b0; x3=1'b1;x4=1'b1;
	#20;
	x1=1'b1; x2=1'b1; x3=1'b0;x4=1'b0;
	#20;
	x1=1'b1; x2=1'b1; x3=1'b0;x4=1'b1;
	#20;
	x1=1'b1; x2=1'b1; x3=1'b1;x4=1'b0;
	#20;
	x1=1'b1; x2=1'b1; x3=1'b1;x4=1'b1;
	#20;

	
	$display("Test complete");
end

endmodule

Debrato_IT_A_62_DISL/Lab_2/ex3/ex3_tb.vcd
$date
	Tue Aug  5 09:44:08 2025
$end
$version
	Icarus Verilog
$end
$timescale
	1ns
$end
$scope module ex3_tb $end
$var wire 1 ! f $end
$var reg 1 " x1 $end
$var reg 1 # x2 $end
$var reg 1 $ x3 $end
$var reg 1 % x4 $end
$scope module ex $end
$var wire 1 ! f $end
$var wire 1 " x1 $end
$var wire 1 # x2 $end
$var wire 1 $ x3 $end
$var wire 1 % x4 $end
$upscope $end
$upscope $end
$enddefinitions $end
#0
$dumpvars
0%
0$
0#
0"
0!
$end
#20
1%
#40
0%
1$
#60
1%
#80
0%
0$
1#
#100
1%
#120
0%
1$
#140
1!
1%
#160
0!
0%
0$
0#
1"
#180
1%
#200
0%
1$
#220
1!
1%
#240
0!
0%
0$
1#
#260
1!
1%
#280
0%
1$
#300
1%
