Debrato_IT_A_62/Debrato_IT_A_62_DISL/Lab_6/Q4/priority_encoder4to2.v
module priority_encoder4to2(
    input wire [3:0] in,
    output reg [1:0] out,
    output reg valid
);

always @(*) begin
    casex(in)
        4'b1xxx: begin out = 2'b11; valid = 1; end
        4'b01xx: begin out = 2'b10; valid = 1; end
        4'b001x: begin out = 2'b01; valid = 1; end
        4'b0001: begin out = 2'b00; valid = 1; end
        default: begin out = 2'b00; valid = 0; end
    endcase
end

endmodule

Debrato_IT_A_62/Debrato_IT_A_62_DISL/Lab_6/Q4/priority_encoder4to2_tb.v
`timescale 1ns/1ps
`include "priority_encoder4to2.v"
module priority_encoder4to2_tb;

reg [3:0] in;
wire [1:0] out;
wire valid;

priority_encoder4to2 DUT (
    .in(in),
    .out(out),
    .valid(valid)
);

initial begin
    $dumpfile("priority_encoder4to2_tb.vcd");
    $dumpvars(0, priority_encoder4to2_tb);

    in = 4'b0000; #10;
    in = 4'b0001; #10;
    in = 4'b0010; #10;
    in = 4'b0011; #10;
    in = 4'b0100; #10;
    in = 4'b0101; #10;
    in = 4'b0111; #10;
    in = 4'b1000; #10;
    in = 4'b1010; #10;
    in = 4'b1111; #10;

    $finish;
end

initial begin
    $monitor("Time=%0t in=%b out=%b valid=%b", $time, in, out, valid);
end

endmodule

Debrato_IT_A_62/Debrato_IT_A_62_DISL/Lab_6/Q4/priority_encoder4to2_tb.vcd
$date
	Tue Sep 23 09:42:17 2025
$end
$version
	Icarus Verilog
$end
$timescale
	1ps
$end
$scope module priority_encoder4to2_tb $end
$var wire 1 ! valid $end
$var wire 2 " out [1:0] $end
$var reg 4 # in [3:0] $end
$scope module DUT $end
$var wire 4 $ in [3:0] $end
$var reg 2 % out [1:0] $end
$var reg 1 ! valid $end
$upscope $end
$upscope $end
$enddefinitions $end
$comment Show the parameter values. $end
$dumpall
$end
#0
$dumpvars
b0 %
b0 $
b0 #
b0 "
0!
$end
#10000
1!
b1 #
b1 $
#20000
b1 "
b1 %
b10 #
b10 $
#30000
b11 #
b11 $
#40000
b10 "
b10 %
b100 #
b100 $
#50000
b101 #
b101 $
#60000
b111 #
b111 $
#70000
b11 "
b11 %
b1000 #
b1000 $
#80000
b1010 #
b1010 $
#90000
b1111 #
b1111 $
