Debrato_IT_A_62/Debrato_IT_A_62_DISL/Lab_6/Q3/decoder4to16.v
module decoder2to4 (
    input wire en,           
    input wire [1:0] in,      
    output reg [3:0] y     
);

always @(*) begin
    if (en) begin
        case (in)
            2'b00: y = 4'b1110;  
            2'b01: y = 4'b1101;  
            2'b10: y = 4'b1011;  
            2'b11: y = 4'b0111; 
            default: y = 4'b1111; 
        endcase
    end
    else begin
        y = 4'b1111; 
    end
end

endmodule


module decoder4to16 (
    input wire en,            
    input wire [3:0] in,      
    output wire [15:0] y     
);

wire [3:0] y0, y1, y2, y3; 
wire en0 = en & (in[3:2] == 2'b00);
wire en1 = en & (in[3:2] == 2'b01);
wire en2 = en & (in[3:2] == 2'b10);
wire en3 = en & (in[3:2] == 2'b11);

decoder2to4 dec0 (.en(en0), .in(in[1:0]), .y(y0));
decoder2to4 dec1 (.en(en1), .in(in[1:0]), .y(y1));
decoder2to4 dec2 (.en(en2), .in(in[1:0]), .y(y2));
decoder2to4 dec3 (.en(en3), .in(in[1:0]), .y(y3));

assign y = {y3, y2, y1, y0};

endmodule

Debrato_IT_A_62/Debrato_IT_A_62_DISL/Lab_6/Q3/decoder4to16_tb.v
`timescale 1ns/1ns
`include "decoder4to16.v"
module decoder4to16_tb;

reg en;
reg [3:0] in;
wire [15:0] y;
 
decoder4to16 DUT (
    .en(en),
    .in(in),
    .y(y)
);

initial begin
    $dumpfile("decoder4to16_tb.vcd");
    $dumpvars(0, decoder4to16_tb);

    en = 0;
    in = 4'b0000;
    #10;
 
    en = 1;
    for (integer i = 0; i < 16; i = i + 1) begin
        in = i;
        #10;
    end
 
    en = 0;
    #10;

    $finish;
end

initial begin
    $monitor("Time=%0t | en=%b | in=%b | y=%b", $time, en, in, y);
end

endmodule

Debrato_IT_A_62/Debrato_IT_A_62_DISL/Lab_6/Q3/decoder4to16_tb.vcd
$date
	Tue Sep 23 09:29:07 2025
$end
$version
	Icarus Verilog
$end
$timescale
	1ns
$end
$scope module decoder4to16_tb $end
$var wire 16 ! y [15:0] $end
$var reg 1 " en $end
$var reg 4 # in [3:0] $end
$scope module DUT $end
$var wire 1 " en $end
$var wire 1 $ en0 $end
$var wire 1 % en1 $end
$var wire 1 & en2 $end
$var wire 1 ' en3 $end
$var wire 4 ( in [3:0] $end
$var wire 4 ) y3 [3:0] $end
$var wire 4 * y2 [3:0] $end
$var wire 4 + y1 [3:0] $end
$var wire 4 , y0 [3:0] $end
$var wire 16 - y [15:0] $end
$scope module dec0 $end
$var wire 1 $ en $end
$var wire 2 . in [1:0] $end
$var reg 4 / y [3:0] $end
$upscope $end
$scope module dec1 $end
$var wire 1 % en $end
$var wire 2 0 in [1:0] $end
$var reg 4 1 y [3:0] $end
$upscope $end
$scope module dec2 $end
$var wire 1 & en $end
$var wire 2 2 in [1:0] $end
$var reg 4 3 y [3:0] $end
$upscope $end
$scope module dec3 $end
$var wire 1 ' en $end
$var wire 2 4 in [1:0] $end
$var reg 4 5 y [3:0] $end
$upscope $end
$upscope $end
$scope begin $ivl_for_loop0 $end
$var integer 32 6 i [31:0] $end
$upscope $end
$upscope $end
$enddefinitions $end
$comment Show the parameter values. $end
$dumpall
$end
#0
$dumpvars
bx 6
b1111 5
b0 4
b1111 3
b0 2
b1111 1
b0 0
b1111 /
b0 .
b1111111111111111 -
b1111 ,
b1111 +
b1111 *
b1111 )
b0 (
0'
0&
0%
0$
b0 #
0"
b1111111111111111 !
$end
#10
b1111111111111110 !
b1111111111111110 -
b1110 ,
b1110 /
1$
b0 6
1"
#20
b1111111111111101 !
b1111111111111101 -
b1101 ,
b1101 /
b1 .
b1 0
b1 2
b1 4
b1 #
b1 (
b1 6
#30
b1111111111111011 !
b1111111111111011 -
b1011 ,
b1011 /
b10 .
b10 0
b10 2
b10 4
b10 #
b10 (
b10 6
#40
b1111111111110111 !
b1111111111110111 -
b111 ,
b111 /
b11 .
b11 0
b11 2
b11 4
b11 #
b11 (
b11 6
#50
b1110 +
b1110 1
0$
1%
b1111111111101111 !
b1111111111101111 -
b1111 ,
b1111 /
b0 .
b0 0
b0 2
b0 4
b100 #
b100 (
b100 6
#60
b1111111111011111 !
b1111111111011111 -
b1101 +
b1101 1
b1 .
b1 0
b1 2
b1 4
b101 #
b101 (
b101 6
#70
b1111111110111111 !
b1111111110111111 -
b1011 +
b1011 1
b10 .
b10 0
b10 2
b10 4
b110 #
b110 (
b110 6
#80
b1111111101111111 !
b1111111101111111 -
b111 +
b111 1
b11 .
b11 0
b11 2
b11 4
b111 #
b111 (
b111 6
#90
b1110 *
b1110 3
0%
1&
b1111111011111111 !
b1111111011111111 -
b1111 +
b1111 1
b0 .
b0 0
b0 2
b0 4
b1000 #
b1000 (
b1000 6
#100
b1111110111111111 !
b1111110111111111 -
b1101 *
b1101 3
b1 .
b1 0
b1 2
b1 4
b1001 #
b1001 (
b1001 6
#110
b1111101111111111 !
b1111101111111111 -
b1011 *
b1011 3
b10 .
b10 0
b10 2
b10 4
b1010 #
b1010 (
b1010 6
#120
b1111011111111111 !
b1111011111111111 -
b111 *
b111 3
b11 .
b11 0
b11 2
b11 4
b1011 #
b1011 (
b1011 6
#130
b1110 )
b1110 5
0&
1'
b1110111111111111 !
b1110111111111111 -
b1111 *
b1111 3
b0 .
b0 0
b0 2
b0 4
b1100 #
b1100 (
b1100 6
#140
b1101111111111111 !
b1101111111111111 -
b1101 )
b1101 5
b1 .
b1 0
b1 2
b1 4
b1101 #
b1101 (
b1101 6
#150
b1011111111111111 !
b1011111111111111 -
b1011 )
b1011 5
b10 .
b10 0
b10 2
b10 4
b1110 #
b1110 (
b1110 6
#160
b111111111111111 !
b111111111111111 -
b111 )
b111 5
b11 .
b11 0
b11 2
b11 4
b1111 #
b1111 (
b1111 6
#170
b1111111111111111 !
b1111111111111111 -
b1111 )
b1111 5
0'
0"
b10000 6
